sh_copilot/__init__.py
sh_copilot/cli.py
sh_copilot/config.py
sh_copilot/copilot.py
sh_copilot/ai/__init__.py
sh_copilot/ai/context.py
sh_copilot/ai/models/__init__.py
sh_copilot/ai/models/base.py
sh_copilot/ai/models/fake.py
sh_copilot/ai/models/openai.py
sh_copilot-0.1.0.dist-info/LICENSE
sh_copilot-0.1.0.dist-info/METADATA
sh_copilot-0.1.0.dist-info/WHEEL
sh_copilot-0.1.0.dist-info/entry_points.txt
sh_copilot-0.1.0.dist-info/top_level.txt
sh_copilot-0.1.0.dist-info/RECORD
